[
	{
		"nome": "Jayme Kemp",
		"email": "quam.curabitur@protonmail.edu",
		"endereco": "658-7635 Ut Avenue",
		"telefone": "(678) 312-8346"
	},
	{
		"nome": "Byron Mullins",
		"email": "ornare.libero@protonmail.ca",
		"endereco": "Ap #542-1198 Lacus. Ave",
		"telefone": "1-793-438-3894"
	},
	{
		"nome": "Victoria Conway",
		"email": "in@aol.edu",
		"endereco": "Ap #746-1889 Eget Avenue",
		"telefone": "1-416-852-1290"
	},
	{
		"nome": "Sandra Daniel",
		"email": "etiam@google.org",
		"endereco": "216-9891 Eleifend Avenue",
		"telefone": "1-549-837-6172"
	},
	{
		"nome": "Thane Valenzuela",
		"email": "justo.sit.amet@icloud.ca",
		"endereco": "687-8528 Hymenaeos. St.",
		"telefone": "1-602-453-0046"
	},
	{
		"nome": "Iola Whitaker",
		"email": "dolor@aol.com",
		"endereco": "840-4353 Lectus Av.",
		"telefone": "(362) 220-9441"
	},
	{
		"nome": "Barbara Wells",
		"email": "placerat.cras.dictum@google.com",
		"endereco": "Ap #327-4094 Sit Avenue",
		"telefone": "(391) 422-3743"
	},
	{
		"nome": "Adele Palmer",
		"email": "fusce@outlook.edu",
		"endereco": "P.O. Box 586, 4971 Eu Street",
		"telefone": "(675) 201-2327"
	},
	{
		"nome": "Edan Rosa",
		"email": "felis@outlook.edu",
		"endereco": "1162 Hendrerit Rd.",
		"telefone": "(986) 188-9511"
	},
	{
		"nome": "Mercedes Gordon",
		"email": "vitae.sodales@yahoo.net",
		"endereco": "Ap #398-5652 Augue Rd.",
		"telefone": "(557) 120-4051"
	},
	{
		"nome": "Nayda Knapp",
		"email": "lectus.cum.sociis@protonmail.couk",
		"endereco": "649-5098 Non St.",
		"telefone": "1-668-461-3767"
	},
	{
		"nome": "Gray Alexander",
		"email": "fringilla.ornare@hotmail.edu",
		"endereco": "538-4606 Nulla Av.",
		"telefone": "(584) 568-7595"
	},
	{
		"nome": "Orlando Dotson",
		"email": "convallis.ante@google.com",
		"endereco": "380-8404 Vulputate, Street",
		"telefone": "1-356-547-8467"
	},
	{
		"nome": "Angelica Browning",
		"email": "tellus.non@protonmail.com",
		"endereco": "587-1094 Malesuada Rd.",
		"telefone": "1-739-719-8346"
	},
	{
		"nome": "Elvis Dickerson",
		"email": "elit.curabitur@aol.com",
		"endereco": "Ap #559-3200 Nec Av.",
		"telefone": "1-313-594-1544"
	},
	{
		"nome": "Beverly Chambers",
		"email": "dictum.ultricies@google.net",
		"endereco": "9729 Sodales St.",
		"telefone": "(868) 765-8169"
	},
	{
		"nome": "Xander Stuart",
		"email": "nulla.vulputate.dui@google.edu",
		"endereco": "P.O. Box 439, 3626 Fringilla Street",
		"telefone": "(607) 728-0656"
	},
	{
		"nome": "Hedley Carter",
		"email": "sagittis.placerat.cras@aol.org",
		"endereco": "Ap #135-8734 Nisl. Rd.",
		"telefone": "1-501-591-2601"
	},
	{
		"nome": "Talon Melton",
		"email": "semper.erat@hotmail.couk",
		"endereco": "P.O. Box 762, 3483 Gravida St.",
		"telefone": "1-487-321-3823"
	},
	{
		"nome": "Patrick Turner",
		"email": "laoreet.ipsum.curabitur@yahoo.ca",
		"endereco": "6627 Libero Road",
		"telefone": "(414) 326-6542"
	}
]